{
  "_class": "group",
  "booleanOperation": -1,
  "clippingMaskMode": 0,
  "do_objectID": "48F08568-F08F-41A7-8225-900A9099CAD5",
  "exportOptions": {
    "_class": "exportOptions",
    "exportFormats": [
    ],
    "includedLayerIds": [
    ],
    "layerOptions": 0,
    "shouldTrim": false
  },
  "frame": {
    "_class": "rect",
    "constrainProportions": false,
    "height": 24,
    "width": 76,
    "x": 0,
    "y": 0
  },
  "groupLayout": {
    "_class": "MSImmutableFreeformGroupLayout"
  },
  "hasClickThrough": false,
  "hasClippingMask": false,
  "isFixedToViewport": false,
  "isFlippedHorizontal": false,
  "isFlippedVertical": false,
  "isLocked": false,
  "isVisible": true,
  "layerListExpandedType": 0,
  "layers": [
    {
      "class": "group",
      "id": "D1081F84-0BFD-45CE-8E75-12AB0226D7E1"
    }
  ],
  "name": "图标颜色备份",
  "nameIsFixed": false,
  "resizingConstraint": 63,
  "resizingType": 0,
  "rotation": 0,
  "shouldBreakMaskChain": false,
  "style": {
    "_class": "style",
    "blur": {
      "_class": "blur",
      "center": "{0.5, 0.5}",
      "isEnabled": false,
      "motionAngle": 0,
      "radius": 10,
      "saturation": 1,
      "type": 0
    },
    "borderOptions": {
      "_class": "borderOptions",
      "dashPattern": [
      ],
      "isEnabled": true,
      "lineCapStyle": 0,
      "lineJoinStyle": 0
    },
    "borders": [
    ],
    "colorControls": {
      "_class": "colorControls",
      "brightness": 0,
      "contrast": 1,
      "hue": 0,
      "isEnabled": false,
      "saturation": 1
    },
    "contextSettings": {
      "_class": "graphicsContextSettings",
      "blendMode": 0,
      "opacity": 1
    },
    "do_objectID": "38365A55-9E3B-47C5-B39F-627EF6BB6A95",
    "endMarkerType": 0,
    "fills": [
    ],
    "innerShadows": [
    ],
    "miterLimit": 10,
    "shadows": [
    ],
    "startMarkerType": 0,
    "windingRule": 1
  },
  "userInfo": {
    "com.bohemiancoding.sketchtool.detach": {
      "symbolInstance": {
        "do_objectID": "64A74BFA-FB17-43B8-B0CA-2A0C06E5DC11",
        "frame": {
          "_class": "rect",
          "constrainProportions": false,
          "height": 24,
          "width": 76,
          "x": 0,
          "y": 0
        }
      },
      "symbolMaster": {
        "do_objectID": "5FBE2C93-B6B5-4662-A4D2-E3CC51EE54A4",
        "symbolID": "92AB6018-338A-4DED-8139-8ED49AFB7A86"
      }
    },
    "com.sketch.detach": {
      "symbolInstance": {
        "do_objectID": "64A74BFA-FB17-43B8-B0CA-2A0C06E5DC11",
        "frame": {
          "_class": "rect",
          "constrainProportions": false,
          "height": 24,
          "width": 76,
          "x": 0,
          "y": 0
        }
      },
      "symbolMaster": {
        "do_objectID": "5FBE2C93-B6B5-4662-A4D2-E3CC51EE54A4",
        "symbolID": "92AB6018-338A-4DED-8139-8ED49AFB7A86"
      }
    }
  }
}