{
  "_class": "group",
  "booleanOperation": -1,
  "clippingMaskMode": 0,
  "do_objectID": "09D46FE0-FAC8-4D5A-9F38-6A45504116D7",
  "exportOptions": {
    "_class": "exportOptions",
    "exportFormats": [
    ],
    "includedLayerIds": [
    ],
    "layerOptions": 0,
    "shouldTrim": false
  },
  "frame": {
    "_class": "rect",
    "constrainProportions": false,
    "height": 30,
    "width": 29,
    "x": 1435,
    "y": 682.9999999999999
  },
  "groupLayout": {
    "_class": "MSImmutableFreeformGroupLayout"
  },
  "hasClickThrough": false,
  "hasClippingMask": false,
  "isFixedToViewport": false,
  "isFlippedHorizontal": false,
  "isFlippedVertical": false,
  "isLocked": false,
  "isVisible": true,
  "layerListExpandedType": 0,
  "layers": [
    {
      "class": "shapeGroup",
      "id": "68AE866D-B1E2-4783-9B1C-F731CAD18644"
    },
    {
      "class": "shapeGroup",
      "id": "65A6362E-468B-4E8E-91B2-036A2D1493D0"
    },
    {
      "class": "shapeGroup",
      "id": "251417E8-AF93-472E-ACE4-21761F8A2E6A"
    },
    {
      "class": "shapeGroup",
      "id": "E720FA3F-2837-40F9-BE03-4875332FC8D6"
    },
    {
      "class": "shapeGroup",
      "id": "86FD7E59-AEF2-4FD0-820F-1B3DACFB2EC2"
    },
    {
      "class": "text",
      "id": "2DC57D94-3B3B-4A8A-8BD5-2F27ECB1776B"
    }
  ],
  "name": "#spacing-horizontal-39D67298-3A61-4A97-B883-9D7EAB10E3D8-A943E9A2-556C-49BA-B338-B4DC34171D11",
  "nameIsFixed": false,
  "resizingConstraint": 63,
  "resizingType": 0,
  "rotation": 0,
  "shouldBreakMaskChain": false,
  "style": {
    "_class": "style",
    "blur": {
      "_class": "blur",
      "center": "{0.5, 0.5}",
      "isEnabled": false,
      "motionAngle": 0,
      "radius": 10,
      "saturation": 1,
      "type": 0
    },
    "borderOptions": {
      "_class": "borderOptions",
      "dashPattern": [
      ],
      "isEnabled": true,
      "lineCapStyle": 0,
      "lineJoinStyle": 0
    },
    "borders": [
    ],
    "colorControls": {
      "_class": "colorControls",
      "brightness": 0,
      "contrast": 1,
      "hue": 0,
      "isEnabled": false,
      "saturation": 1
    },
    "contextSettings": {
      "_class": "graphicsContextSettings",
      "blendMode": 0,
      "opacity": 1
    },
    "do_objectID": "6784796F-0242-4293-B6B5-AD1BEDA0809C",
    "endMarkerType": 0,
    "fills": [
    ],
    "innerShadows": [
    ],
    "miterLimit": 10,
    "shadows": [
    ],
    "startMarkerType": 0,
    "windingRule": 1
  }
}