{
  "_class": "symbolMaster",
  "allowsOverrides": true,
  "backgroundColor": {
    "_class": "color",
    "alpha": 1,
    "blue": 0,
    "green": 0,
    "red": 0
  },
  "booleanOperation": -1,
  "clippingMaskMode": 0,
  "do_objectID": "03DA5AA2-CB17-4893-846F-AEDF21608F5F",
  "exportOptions": {
    "_class": "exportOptions",
    "exportFormats": [
    ],
    "includedLayerIds": [
    ],
    "layerOptions": 0,
    "shouldTrim": false
  },
  "frame": {
    "_class": "rect",
    "constrainProportions": false,
    "height": 116,
    "width": 240,
    "x": 3705,
    "y": 161
  },
  "groupLayout": {
    "_class": "MSImmutableFreeformGroupLayout"
  },
  "hasBackgroundColor": true,
  "hasClickThrough": true,
  "hasClippingMask": false,
  "horizontalRulerData": {
    "_class": "rulerData",
    "base": 0,
    "guides": [
    ]
  },
  "includeBackgroundColorInExport": false,
  "includeBackgroundColorInInstance": false,
  "isFixedToViewport": false,
  "isFlippedHorizontal": false,
  "isFlippedVertical": false,
  "isFlowHome": false,
  "isLocked": false,
  "isVisible": true,
  "layerListExpandedType": 0,
  "layers": [
    {
      "class": "shapeGroup",
      "id": "FA663FE9-2C83-4358-BEB5-7A0561F56AC1"
    }
  ],
  "name": "04. Data Display 数据展示/Menu菜单/气泡/左",
  "nameIsFixed": true,
  "overrideProperties": [
  ],
  "presetDictionary": {
  },
  "resizesContent": false,
  "resizingConstraint": 63,
  "resizingType": 0,
  "rotation": 0,
  "shouldBreakMaskChain": true,
  "style": {
    "_class": "style",
    "blur": {
      "_class": "blur",
      "center": "{0.5, 0.5}",
      "isEnabled": false,
      "motionAngle": 0,
      "radius": 10,
      "saturation": 1,
      "type": 0
    },
    "borderOptions": {
      "_class": "borderOptions",
      "dashPattern": [
      ],
      "isEnabled": true,
      "lineCapStyle": 0,
      "lineJoinStyle": 0
    },
    "borders": [
    ],
    "colorControls": {
      "_class": "colorControls",
      "brightness": 0,
      "contrast": 1,
      "hue": 0,
      "isEnabled": false,
      "saturation": 1
    },
    "contextSettings": {
      "_class": "graphicsContextSettings",
      "blendMode": 0,
      "opacity": 1
    },
    "do_objectID": "CBAB3EAC-7D6C-44A9-A1EE-96B800D13CED",
    "endMarkerType": 0,
    "fills": [
    ],
    "innerShadows": [
    ],
    "miterLimit": 10,
    "shadows": [
    ],
    "startMarkerType": 0,
    "windingRule": 1
  },
  "symbolID": "6C40A6E3-AE8C-446C-ACD4-DD3985B3AB35",
  "verticalRulerData": {
    "_class": "rulerData",
    "base": 0,
    "guides": [
    ]
  }
}