{
  "_class": "slice",
  "backgroundColor": {
    "_class": "color",
    "alpha": 1,
    "blue": 1,
    "green": 1,
    "red": 1
  },
  "booleanOperation": -1,
  "do_objectID": "B543A84E-ECAB-48E9-A21A-DF7782D6DB67",
  "exportOptions": {
    "_class": "exportOptions",
    "exportFormats": [
      {
        "_class": "exportFormat",
        "absoluteSize": 0,
        "fileFormat": "svg",
        "name": "",
        "namingScheme": 0,
        "scale": 20,
        "visibleScaleType": 0
      }
    ],
    "includedLayerIds": [
    ],
    "layerOptions": 2,
    "shouldTrim": false
  },
  "frame": {
    "_class": "rect",
    "constrainProportions": true,
    "height": 64,
    "width": 64,
    "x": 0,
    "y": 0
  },
  "hasBackgroundColor": false,
  "isFixedToViewport": false,
  "isFlippedHorizontal": false,
  "isFlippedVertical": false,
  "isLocked": false,
  "isVisible": true,
  "layerListExpandedType": 0,
  "name": "D-015-L",
  "nameIsFixed": true,
  "resizingConstraint": 63,
  "resizingType": 0,
  "rotation": 0,
  "shouldBreakMaskChain": false,
  "userInfo": {
    "com.animaapp.stc-sketch-plugin": {
      "kModelPropertiesKey": {
        "constraints": {
          "aspectRatio": {
            "constant": 64,
            "enabled": 1,
            "modelID": "constraint_07732e6d-1deb-4557-abec-bb0ed643f19c",
            "model_class": "ADModelConstraint",
            "model_version": 0,
            "multiplier": 64
          },
          "automatic": 1,
          "modelID": "viewConstraints_eb0ccfaa-f923-4d5f-b4d5-468adba82bff",
          "model_class": "ADModelViewConstraints",
          "model_version": 0,
          "scaleFactor": 1
        }
      }
    }
  }
}